{
  "slug": "radio-buttons",
  "demo": "SizeRadioButtons",
  "passedRules": [
    "aria-allowed-attr",
    "aria-conditional-attr",
    "aria-hidden-focus",
    "aria-prohibited-attr",
    "aria-valid-attr",
    "aria-valid-attr-value",
    "form-field-multiple-labels",
    "nested-interactive",
    "target-size"
  ],
  "failedRules": ["label"],
  "testedRules": {
    "wcag2a": [
      "aria-allowed-attr",
      "aria-conditional-attr",
      "aria-hidden-focus",
      "aria-prohibited-attr",
      "aria-valid-attr-value",
      "aria-valid-attr",
      "form-field-multiple-labels",
      "nested-interactive",
      "label"
    ],
    "wcag22aa": ["target-size"]
  }
}
